[
   {
      "user": "https://github.com/brendanray",
      "repos": [
         {
            "url": "https://github.com/brendanray/webcrawler",
            "ssh_url": "git@github.com:brendanray/webcrawler.git",
            "language": ""
         }
      ]
   },
   {
      "user": "https://github.com/MalenaPAZ",
      "repos": [
         {
            "url": "https://github.com/MalenaPAZ/PROJET_PISCINE",
            "ssh_url": "git@github.com:MalenaPAZ/PROJET_PISCINE.git",
            "language": "PHP"
         },
         {
            "url": "https://github.com/MalenaPAZ/REP1",
            "ssh_url": "git@github.com:MalenaPAZ/REP1.git",
            "language": ""
         }
      ]
   },
   {
      "user": "https://github.com/meghankennedy",
      "repos": [
         {
            "url": "https://github.com/meghankennedy/llama-lime",
            "ssh_url": "git@github.com:meghankennedy/llama-lime.git",
            "language": ""
         },
         {
            "url": "https://github.com/meghankennedy/meghankennedy.github.io",
            "ssh_url": "git@github.com:meghankennedy/meghankennedy.github.io.git",
            "language": "JavaScript"
         }
      ]
   },
   {
      "user": "https://github.com/ruthgarcia",
      "repos": [
         {
            "url": "https://github.com/ruthgarcia/quetzal",
            "ssh_url": "git@github.com:ruthgarcia/quetzal.git",
            "language": "CSS"
         },
         {
            "url": "https://github.com/ruthgarcia/ruthg-eis20132",
            "ssh_url": "git@github.com:ruthgarcia/ruthg-eis20132.git",
            "language": "Ruby"
         }
      ]
   }
]