[
   {
      "user": "https://github.com/aaqaishtyaq",
      "repos": [
         {
            "url": "https://github.com/aaqaishtyaq/float",
            "ssh_url": "git@github.com:aaqaishtyaq/float.git",
            "language": "Go"
         },
         {
            "url": "https://github.com/aaqaishtyaq/dotfiles",
            "ssh_url": "git@github.com:aaqaishtyaq/dotfiles.git",
            "language": "Shell"
         },
         {
            "url": "https://github.com/aaqaishtyaq/iay",
            "ssh_url": "git@github.com:aaqaishtyaq/iay.git",
            "language": "Rust"
         },
         {
            "url": "https://github.com/aaqaishtyaq/WebGL-Fluid-Simulation",
            "ssh_url": "git@github.com:aaqaishtyaq/WebGL-Fluid-Simulation.git",
            "language": "JavaScript"
         },
         {
            "url": "https://github.com/aaqaishtyaq/aoc",
            "ssh_url": "git@github.com:aaqaishtyaq/aoc.git",
            "language": "Go"
         },
         {
            "url": "https://github.com/aaqaishtyaq/aaqaishtyaq.github.io",
            "ssh_url": "git@github.com:aaqaishtyaq/aaqaishtyaq.github.io.git",
            "language": "HTML"
         },
         {
            "url": "https://github.com/aaqaishtyaq/Python",
            "ssh_url": "git@github.com:aaqaishtyaq/Python.git",
            "language": "Python"
         },
         {
            "url": "https://github.com/aaqaishtyaq/lab",
            "ssh_url": "git@github.com:aaqaishtyaq/lab.git",
            "language": "HCL"
         },
         {
            "url": "https://github.com/aaqaishtyaq/theia-rpc-ext",
            "ssh_url": "git@github.com:aaqaishtyaq/theia-rpc-ext.git",
            "language": "TypeScript"
         },
         {
            "url": "https://github.com/aaqaishtyaq/themes-go-acme",
            "ssh_url": "git@github.com:aaqaishtyaq/themes-go-acme.git",
            "language": "TypeScript"
         },
         {
            "url": "https://github.com/aaqaishtyaq/home_ops",
            "ssh_url": "git@github.com:aaqaishtyaq/home_ops.git",
            "language": "Nix"
         },
         {
            "url": "https://github.com/aaqaishtyaq/roxxy",
            "ssh_url": "git@github.com:aaqaishtyaq/roxxy.git",
            "language": "Go"
         },
         {
            "url": "https://github.com/aaqaishtyaq/gmux",
            "ssh_url": "git@github.com:aaqaishtyaq/gmux.git",
            "language": "Go"
         },
         {
            "url": "https://github.com/aaqaishtyaq/dockerfiles",
            "ssh_url": "git@github.com:aaqaishtyaq/dockerfiles.git",
            "language": "Dockerfile"
         },
         {
            "url": "https://github.com/aaqaishtyaq/openvscode-server-arm",
            "ssh_url": "git@github.com:aaqaishtyaq/openvscode-server-arm.git",
            "language": "Dockerfile"
         },
         {
            "url": "https://github.com/aaqaishtyaq/dang-vscode",
            "ssh_url": "git@github.com:aaqaishtyaq/dang-vscode.git",
            "language": ""
         },
         {
            "url": "https://github.com/aaqaishtyaq/react-playground",
            "ssh_url": "git@github.com:aaqaishtyaq/react-playground.git",
            "language": "TypeScript"
         },
         {
            "url": "https://github.com/aaqaishtyaq/temporal-example",
            "ssh_url": "git@github.com:aaqaishtyaq/temporal-example.git",
            "language": "Go"
         },
         {
            "url": "https://github.com/aaqaishtyaq/task-plugin",
            "ssh_url": "git@github.com:aaqaishtyaq/task-plugin.git",
            "language": "TypeScript"
         },
         {
            "url": "https://github.com/aaqaishtyaq/dais",
            "ssh_url": "git@github.com:aaqaishtyaq/dais.git",
            "language": "Shell"
         },
         {
            "url": "https://github.com/aaqaishtyaq/homebrew-tap",
            "ssh_url": "git@github.com:aaqaishtyaq/homebrew-tap.git",
            "language": "Go"
         },
         {
            "url": "https://github.com/aaqaishtyaq/sudoranger",
            "ssh_url": "git@github.com:aaqaishtyaq/sudoranger.git",
            "language": "Go"
         },
         {
            "url": "https://github.com/aaqaishtyaq/goinode",
            "ssh_url": "git@github.com:aaqaishtyaq/goinode.git",
            "language": "Go"
         },
         {
            "url": "https://github.com/aaqaishtyaq/put-up-pi",
            "ssh_url": "git@github.com:aaqaishtyaq/put-up-pi.git",
            "language": "Jinja"
         },
         {
            "url": "https://github.com/aaqaishtyaq/http-echo",
            "ssh_url": "git@github.com:aaqaishtyaq/http-echo.git",
            "language": "Go"
         },
         {
            "url": "https://github.com/aaqaishtyaq/git-link",
            "ssh_url": "git@github.com:aaqaishtyaq/git-link.git",
            "language": "Go"
         },
         {
            "url": "https://github.com/aaqaishtyaq/dark-alliance",
            "ssh_url": "git@github.com:aaqaishtyaq/dark-alliance.git",
            "language": ""
         },
         {
            "url": "https://github.com/aaqaishtyaq/slides",
            "ssh_url": "git@github.com:aaqaishtyaq/slides.git",
            "language": "JavaScript"
         },
         {
            "url": "https://github.com/aaqaishtyaq/ip-check",
            "ssh_url": "git@github.com:aaqaishtyaq/ip-check.git",
            "language": "Shell"
         },
         {
            "url": "https://github.com/aaqaishtyaq/galactus",
            "ssh_url": "git@github.com:aaqaishtyaq/galactus.git",
            "language": "Go"
         },
         {
            "url": "https://github.com/aaqaishtyaq/container-lab",
            "ssh_url": "git@github.com:aaqaishtyaq/container-lab.git",
            "language": "HCL"
         },
         {
            "url": "https://github.com/aaqaishtyaq/flappy_bird",
            "ssh_url": "git@github.com:aaqaishtyaq/flappy_bird.git",
            "language": "JavaScript"
         },
         {
            "url": "https://github.com/aaqaishtyaq/pydelhi-git",
            "ssh_url": "git@github.com:aaqaishtyaq/pydelhi-git.git",
            "language": ""
         },
         {
            "url": "https://github.com/aaqaishtyaq/cgit",
            "ssh_url": "git@github.com:aaqaishtyaq/cgit.git",
            "language": "C"
         },
         {
            "url": "https://github.com/aaqaishtyaq/golearn",
            "ssh_url": "git@github.com:aaqaishtyaq/golearn.git",
            "language": "Go"
         },
         {
            "url": "https://github.com/aaqaishtyaq/govanityurls",
            "ssh_url": "git@github.com:aaqaishtyaq/govanityurls.git",
            "language": "Go"
         },
         {
            "url": "https://github.com/aaqaishtyaq/tools",
            "ssh_url": "git@github.com:aaqaishtyaq/tools.git",
            "language": "Go"
         },
         {
            "url": "https://github.com/aaqaishtyaq/rouster",
            "ssh_url": "git@github.com:aaqaishtyaq/rouster.git",
            "language": "Go"
         },
         {
            "url": "https://github.com/aaqaishtyaq/katacoda-scenarios",
            "ssh_url": "git@github.com:aaqaishtyaq/katacoda-scenarios.git",
            "language": ""
         },
         {
            "url": "https://github.com/aaqaishtyaq/percalc",
            "ssh_url": "git@github.com:aaqaishtyaq/percalc.git",
            "language": "CSS"
         },
         {
            "url": "https://github.com/aaqaishtyaq/doc-the-bot",
            "ssh_url": "git@github.com:aaqaishtyaq/doc-the-bot.git",
            "language": "Python"
         },
         {
            "url": "https://github.com/aaqaishtyaq/elixir-gitpod",
            "ssh_url": "git@github.com:aaqaishtyaq/elixir-gitpod.git",
            "language": "Shell"
         },
         {
            "url": "https://github.com/aaqaishtyaq/bookmark-service",
            "ssh_url": "git@github.com:aaqaishtyaq/bookmark-service.git",
            "language": "Go"
         },
         {
            "url": "https://github.com/aaqaishtyaq/nur-packages",
            "ssh_url": "git@github.com:aaqaishtyaq/nur-packages.git",
            "language": "Nix"
         },
         {
            "url": "https://github.com/aaqaishtyaq/guess-game",
            "ssh_url": "git@github.com:aaqaishtyaq/guess-game.git",
            "language": "Python"
         },
         {
            "url": "https://github.com/aaqaishtyaq/servicekit",
            "ssh_url": "git@github.com:aaqaishtyaq/servicekit.git",
            "language": "Go"
         },
         {
            "url": "https://github.com/aaqaishtyaq/theia-run",
            "ssh_url": "git@github.com:aaqaishtyaq/theia-run.git",
            "language": "TypeScript"
         },
         {
            "url": "https://github.com/aaqaishtyaq/gotopdf",
            "ssh_url": "git@github.com:aaqaishtyaq/gotopdf.git",
            "language": "Go"
         },
         {
            "url": "https://github.com/aaqaishtyaq/linkbin",
            "ssh_url": "git@github.com:aaqaishtyaq/linkbin.git",
            "language": "HTML"
         }
      ]
   },
   {
      "user": "https://github.com/AasthaGupta",
      "repos": [
         {
            "url": "https://github.com/AasthaGupta/Twitter-Social-Graph",
            "ssh_url": "git@github.com:AasthaGupta/Twitter-Social-Graph.git",
            "language": "Python"
         },
         {
            "url": "https://github.com/AasthaGupta/Fun-Lyrics",
            "ssh_url": "git@github.com:AasthaGupta/Fun-Lyrics.git",
            "language": "Python"
         },
         {
            "url": "https://github.com/AasthaGupta/ProjectZ",
            "ssh_url": "git@github.com:AasthaGupta/ProjectZ.git",
            "language": "VHDL"
         },
         {
            "url": "https://github.com/AasthaGupta/CodePlus",
            "ssh_url": "git@github.com:AasthaGupta/CodePlus.git",
            "language": "HTML"
         },
         {
            "url": "https://github.com/AasthaGupta/DrinkUp",
            "ssh_url": "git@github.com:AasthaGupta/DrinkUp.git",
            "language": "Swift"
         },
         {
            "url": "https://github.com/AasthaGupta/GANN-Datasets",
            "ssh_url": "git@github.com:AasthaGupta/GANN-Datasets.git",
            "language": ""
         }
      ]
   },
   {
      "user": "https://github.com/AllenKwok",
      "repos": [
         {
            "url": "https://github.com/AllenKwok/XLinkSDK-iOS",
            "ssh_url": "git@github.com:AllenKwok/XLinkSDK-iOS.git",
            "language": "Objective-C"
         }
      ]
   },
   {
      "user": "https://github.com/ankitsharma",
      "repos": [
         {
            "url": "https://github.com/ankitsharma/SpringLearning",
            "ssh_url": "git@github.com:ankitsharma/SpringLearning.git",
            "language": ""
         }
      ]
   },
   {
      "user": "https://github.com/HLyong",
      "repos": [
         {
            "url": "https://github.com/HLyong/learn_OpenGLES",
            "ssh_url": "git@github.com:HLyong/learn_OpenGLES.git",
            "language": "Java"
         },
         {
            "url": "https://github.com/HLyong/HLyong.github.io",
            "ssh_url": "git@github.com:HLyong/HLyong.github.io.git",
            "language": "HTML"
         },
         {
            "url": "https://github.com/HLyong/mineSweeping",
            "ssh_url": "git@github.com:HLyong/mineSweeping.git",
            "language": "JavaScript"
         },
         {
            "url": "https://github.com/HLyong/MusicPlayer",
            "ssh_url": "git@github.com:HLyong/MusicPlayer.git",
            "language": "JavaScript"
         }
      ]
   },
   {
      "user": "https://github.com/hushenbeg",
      "repos": [
         {
            "url": "https://github.com/hushenbeg/python-otp-generator",
            "ssh_url": "git@github.com:hushenbeg/python-otp-generator.git",
            "language": "Python"
         },
         {
            "url": "https://github.com/hushenbeg/odoo_curd_ops",
            "ssh_url": "git@github.com:hushenbeg/odoo_curd_ops.git",
            "language": ""
         },
         {
            "url": "https://github.com/hushenbeg/phone-number-identifier",
            "ssh_url": "git@github.com:hushenbeg/phone-number-identifier.git",
            "language": "Python"
         },
         {
            "url": "https://github.com/hushenbeg/blogs",
            "ssh_url": "git@github.com:hushenbeg/blogs.git",
            "language": "JavaScript"
         },
         {
            "url": "https://github.com/hushenbeg/job_portal",
            "ssh_url": "git@github.com:hushenbeg/job_portal.git",
            "language": "HTML"
         },
         {
            "url": "https://github.com/hushenbeg/water_drink_reminder",
            "ssh_url": "git@github.com:hushenbeg/water_drink_reminder.git",
            "language": ""
         },
         {
            "url": "https://github.com/hushenbeg/simple_calculator_in_python3",
            "ssh_url": "git@github.com:hushenbeg/simple_calculator_in_python3.git",
            "language": "Python"
         },
         {
            "url": "https://github.com/hushenbeg/orm_curd",
            "ssh_url": "git@github.com:hushenbeg/orm_curd.git",
            "language": "Python"
         },
         {
            "url": "https://github.com/hushenbeg/typing_test",
            "ssh_url": "git@github.com:hushenbeg/typing_test.git",
            "language": "JavaScript"
         },
         {
            "url": "https://github.com/hushenbeg/calorietracker",
            "ssh_url": "git@github.com:hushenbeg/calorietracker.git",
            "language": "Python"
         },
         {
            "url": "https://github.com/hushenbeg/read_python",
            "ssh_url": "git@github.com:hushenbeg/read_python.git",
            "language": ""
         },
         {
            "url": "https://github.com/hushenbeg/portal_jobs",
            "ssh_url": "git@github.com:hushenbeg/portal_jobs.git",
            "language": "HTML"
         },
         {
            "url": "https://github.com/hushenbeg/weatherforecast",
            "ssh_url": "git@github.com:hushenbeg/weatherforecast.git",
            "language": "Python"
         },
         {
            "url": "https://github.com/hushenbeg/wishproject",
            "ssh_url": "git@github.com:hushenbeg/wishproject.git",
            "language": "Python"
         },
         {
            "url": "https://github.com/hushenbeg/cvgenerator",
            "ssh_url": "git@github.com:hushenbeg/cvgenerator.git",
            "language": "Python"
         },
         {
            "url": "https://github.com/hushenbeg/csv_data_import",
            "ssh_url": "git@github.com:hushenbeg/csv_data_import.git",
            "language": ""
         },
         {
            "url": "https://github.com/hushenbeg/movie",
            "ssh_url": "git@github.com:hushenbeg/movie.git",
            "language": "Python"
         },
         {
            "url": "https://github.com/hushenbeg/calculates-Love",
            "ssh_url": "git@github.com:hushenbeg/calculates-Love.git",
            "language": "Python"
         },
         {
            "url": "https://github.com/hushenbeg/todo_django",
            "ssh_url": "git@github.com:hushenbeg/todo_django.git",
            "language": "Python"
         },
         {
            "url": "https://github.com/hushenbeg/studentfeedback",
            "ssh_url": "git@github.com:hushenbeg/studentfeedback.git",
            "language": "Python"
         },
         {
            "url": "https://github.com/hushenbeg/voterapp",
            "ssh_url": "git@github.com:hushenbeg/voterapp.git",
            "language": "Python"
         },
         {
            "url": "https://github.com/hushenbeg/todo_list",
            "ssh_url": "git@github.com:hushenbeg/todo_list.git",
            "language": "JavaScript"
         },
         {
            "url": "https://github.com/hushenbeg/newsportal",
            "ssh_url": "git@github.com:hushenbeg/newsportal.git",
            "language": "Python"
         }
      ]
   },
   {
      "user": "https://github.com/maheshm",
      "repos": [
         {
            "url": "https://github.com/maheshm/vfs_reactos",
            "ssh_url": "git@github.com:maheshm/vfs_reactos.git",
            "language": "C"
         },
         {
            "url": "https://github.com/maheshm/otp-in-elixir",
            "ssh_url": "git@github.com:maheshm/otp-in-elixir.git",
            "language": "Elixir"
         },
         {
            "url": "https://github.com/maheshm/my_projects",
            "ssh_url": "git@github.com:maheshm/my_projects.git",
            "language": "Java"
         },
         {
            "url": "https://github.com/maheshm/til",
            "ssh_url": "git@github.com:maheshm/til.git",
            "language": ""
         },
         {
            "url": "https://github.com/maheshm/surveillance-robot",
            "ssh_url": "git@github.com:maheshm/surveillance-robot.git",
            "language": "Java"
         },
         {
            "url": "https://github.com/maheshm/dotemacs",
            "ssh_url": "git@github.com:maheshm/dotemacs.git",
            "language": "Emacs Lisp"
         },
         {
            "url": "https://github.com/maheshm/prime-table",
            "ssh_url": "git@github.com:maheshm/prime-table.git",
            "language": "Ruby"
         },
         {
            "url": "https://github.com/maheshm/b612-pubsub",
            "ssh_url": "git@github.com:maheshm/b612-pubsub.git",
            "language": "Java"
         },
         {
            "url": "https://github.com/maheshm/malayalagrandham",
            "ssh_url": "git@github.com:maheshm/malayalagrandham.git",
            "language": "JavaScript"
         },
         {
            "url": "https://github.com/maheshm/store-stock",
            "ssh_url": "git@github.com:maheshm/store-stock.git",
            "language": "Python"
         },
         {
            "url": "https://github.com/maheshm/railsexpress",
            "ssh_url": "git@github.com:maheshm/railsexpress.git",
            "language": "Dockerfile"
         },
         {
            "url": "https://github.com/maheshm/hurd-installer",
            "ssh_url": "git@github.com:maheshm/hurd-installer.git",
            "language": "Shell"
         },
         {
            "url": "https://github.com/maheshm/dotfiles",
            "ssh_url": "git@github.com:maheshm/dotfiles.git",
            "language": "Shell"
         },
         {
            "url": "https://github.com/maheshm/campytics",
            "ssh_url": "git@github.com:maheshm/campytics.git",
            "language": "Ruby"
         },
         {
            "url": "https://github.com/maheshm/chat_py",
            "ssh_url": "git@github.com:maheshm/chat_py.git",
            "language": "Python"
         },
         {
            "url": "https://github.com/maheshm/closestCommonManager",
            "ssh_url": "git@github.com:maheshm/closestCommonManager.git",
            "language": "Go"
         },
         {
            "url": "https://github.com/maheshm/wifi-tracker",
            "ssh_url": "git@github.com:maheshm/wifi-tracker.git",
            "language": "C"
         },
         {
            "url": "https://github.com/maheshm/UPM",
            "ssh_url": "git@github.com:maheshm/UPM.git",
            "language": "Python"
         },
         {
            "url": "https://github.com/maheshm/langrep",
            "ssh_url": "git@github.com:maheshm/langrep.git",
            "language": "Python"
         },
         {
            "url": "https://github.com/maheshm/b612-wordcloud",
            "ssh_url": "git@github.com:maheshm/b612-wordcloud.git",
            "language": "Java"
         },
         {
            "url": "https://github.com/maheshm/blog",
            "ssh_url": "git@github.com:maheshm/blog.git",
            "language": "HTML"
         },
         {
            "url": "https://github.com/maheshm/elixir-docker",
            "ssh_url": "git@github.com:maheshm/elixir-docker.git",
            "language": "Shell"
         },
         {
            "url": "https://github.com/maheshm/card_tokeniser",
            "ssh_url": "git@github.com:maheshm/card_tokeniser.git",
            "language": "Elixir"
         },
         {
            "url": "https://github.com/maheshm/chat-hub",
            "ssh_url": "git@github.com:maheshm/chat-hub.git",
            "language": "Ruby"
         }
      ]
   },
   {
      "user": "https://github.com/narayanbhadaniya",
      "repos": [
         {
            "url": "https://github.com/narayanbhadaniya/E-technofarm",
            "ssh_url": "git@github.com:narayanbhadaniya/E-technofarm.git",
            "language": "CSS"
         },
         {
            "url": "https://github.com/narayanbhadaniya/Instagram_Profile_Downloader",
            "ssh_url": "git@github.com:narayanbhadaniya/Instagram_Profile_Downloader.git",
            "language": "Python"
         },
         {
            "url": "https://github.com/narayanbhadaniya/My-Bio",
            "ssh_url": "git@github.com:narayanbhadaniya/My-Bio.git",
            "language": ""
         }
      ]
   },
   {
      "user": "https://github.com/nileshjha",
      "repos": [
         {
            "url": "https://github.com/nileshjha/test",
            "ssh_url": "git@github.com:nileshjha/test.git",
            "language": ""
         }
      ]
   },
   {
      "user": "https://github.com/rahulchoudhary",
      "repos": [
         {
            "url": "https://github.com/rahulchoudhary/adventofcode2022",
            "ssh_url": "git@github.com:rahulchoudhary/adventofcode2022.git",
            "language": "Python"
         },
         {
            "url": "https://github.com/rahulchoudhary/adventofcode2021_c-",
            "ssh_url": "git@github.com:rahulchoudhary/adventofcode2021_c-.git",
            "language": "C#"
         }
      ]
   },
   {
      "user": "https://github.com/Rakshitvig",
      "repos": [
         {
            "url": "https://github.com/Rakshitvig/Test",
            "ssh_url": "git@github.com:Rakshitvig/Test.git",
            "language": ""
         },
         {
            "url": "https://github.com/Rakshitvig/coursera-test",
            "ssh_url": "git@github.com:Rakshitvig/coursera-test.git",
            "language": "HTML"
         }
      ]
   },
   {
      "user": "https://github.com/sayanghosh",
      "repos": [
         {
            "url": "https://github.com/sayanghosh/LDA-SCVB0",
            "ssh_url": "git@github.com:sayanghosh/LDA-SCVB0.git",
            "language": "C++"
         },
         {
            "url": "https://github.com/sayanghosh/face-classification",
            "ssh_url": "git@github.com:sayanghosh/face-classification.git",
            "language": "Python"
         },
         {
            "url": "https://github.com/sayanghosh/JessHack14",
            "ssh_url": "git@github.com:sayanghosh/JessHack14.git",
            "language": "Java"
         }
      ]
   },
   {
      "user": "https://github.com/tanyarajhans",
      "repos": [
         {
            "url": "https://github.com/tanyarajhans/LeetCode",
            "ssh_url": "git@github.com:tanyarajhans/LeetCode.git",
            "language": "C++"
         },
         {
            "url": "https://github.com/tanyarajhans/Codeforces",
            "ssh_url": "git@github.com:tanyarajhans/Codeforces.git",
            "language": "C++"
         },
         {
            "url": "https://github.com/tanyarajhans/tanyarajhans",
            "ssh_url": "git@github.com:tanyarajhans/tanyarajhans.git",
            "language": ""
         },
         {
            "url": "https://github.com/tanyarajhans/dog_breed_image_classifier",
            "ssh_url": "git@github.com:tanyarajhans/dog_breed_image_classifier.git",
            "language": "Jupyter Notebook"
         },
         {
            "url": "https://github.com/tanyarajhans/heart_disease_predictor",
            "ssh_url": "git@github.com:tanyarajhans/heart_disease_predictor.git",
            "language": "Jupyter Notebook"
         },
         {
            "url": "https://github.com/tanyarajhans/Actions",
            "ssh_url": "git@github.com:tanyarajhans/Actions.git",
            "language": ""
         },
         {
            "url": "https://github.com/tanyarajhans/ChatsApp",
            "ssh_url": "git@github.com:tanyarajhans/ChatsApp.git",
            "language": "JavaScript"
         },
         {
            "url": "https://github.com/tanyarajhans/Tomato",
            "ssh_url": "git@github.com:tanyarajhans/Tomato.git",
            "language": "JavaScript"
         },
         {
            "url": "https://github.com/tanyarajhans/invisible_cloak",
            "ssh_url": "git@github.com:tanyarajhans/invisible_cloak.git",
            "language": "Python"
         },
         {
            "url": "https://github.com/tanyarajhans/NITA-CP-Website",
            "ssh_url": "git@github.com:tanyarajhans/NITA-CP-Website.git",
            "language": "JavaScript"
         },
         {
            "url": "https://github.com/tanyarajhans/BitcoinTicker",
            "ssh_url": "git@github.com:tanyarajhans/BitcoinTicker.git",
            "language": "Dart"
         },
         {
            "url": "https://github.com/tanyarajhans/memories",
            "ssh_url": "git@github.com:tanyarajhans/memories.git",
            "language": "JavaScript"
         },
         {
            "url": "https://github.com/tanyarajhans/hrms_project",
            "ssh_url": "git@github.com:tanyarajhans/hrms_project.git",
            "language": "JavaScript"
         },
         {
            "url": "https://github.com/tanyarajhans/Todoey",
            "ssh_url": "git@github.com:tanyarajhans/Todoey.git",
            "language": "Dart"
         },
         {
            "url": "https://github.com/tanyarajhans/restaurant_ui_flutter",
            "ssh_url": "git@github.com:tanyarajhans/restaurant_ui_flutter.git",
            "language": "Dart"
         },
         {
            "url": "https://github.com/tanyarajhans/DiceGame",
            "ssh_url": "git@github.com:tanyarajhans/DiceGame.git",
            "language": "Dart"
         },
         {
            "url": "https://github.com/tanyarajhans/Adventini",
            "ssh_url": "git@github.com:tanyarajhans/Adventini.git",
            "language": "Dart"
         },
         {
            "url": "https://github.com/tanyarajhans/Magic8Ball",
            "ssh_url": "git@github.com:tanyarajhans/Magic8Ball.git",
            "language": "Dart"
         },
         {
            "url": "https://github.com/tanyarajhans/instagram-clone",
            "ssh_url": "git@github.com:tanyarajhans/instagram-clone.git",
            "language": ""
         },
         {
            "url": "https://github.com/tanyarajhans/todo-list",
            "ssh_url": "git@github.com:tanyarajhans/todo-list.git",
            "language": "CSS"
         },
         {
            "url": "https://github.com/tanyarajhans/CookBook",
            "ssh_url": "git@github.com:tanyarajhans/CookBook.git",
            "language": "Dart"
         },
         {
            "url": "https://github.com/tanyarajhans/Climax",
            "ssh_url": "git@github.com:tanyarajhans/Climax.git",
            "language": "Dart"
         },
         {
            "url": "https://github.com/tanyarajhans/Shopifie",
            "ssh_url": "git@github.com:tanyarajhans/Shopifie.git",
            "language": "Dart"
         },
         {
            "url": "https://github.com/tanyarajhans/simon-game",
            "ssh_url": "git@github.com:tanyarajhans/simon-game.git",
            "language": "JavaScript"
         },
         {
            "url": "https://github.com/tanyarajhans/Quizzler",
            "ssh_url": "git@github.com:tanyarajhans/Quizzler.git",
            "language": "Dart"
         },
         {
            "url": "https://github.com/tanyarajhans/PowerHer",
            "ssh_url": "git@github.com:tanyarajhans/PowerHer.git",
            "language": ""
         },
         {
            "url": "https://github.com/tanyarajhans/screen-analyzer",
            "ssh_url": "git@github.com:tanyarajhans/screen-analyzer.git",
            "language": "JavaScript"
         },
         {
            "url": "https://github.com/tanyarajhans/BMI-Calculator",
            "ssh_url": "git@github.com:tanyarajhans/BMI-Calculator.git",
            "language": "Dart"
         },
         {
            "url": "https://github.com/tanyarajhans/Flash_Chat",
            "ssh_url": "git@github.com:tanyarajhans/Flash_Chat.git",
            "language": "Dart"
         }
      ]
   },
   {
      "user": "https://github.com/utkarshagarwal",
      "repos": [
         {
            "url": "https://github.com/utkarshagarwal/TwitterRelationExtractor",
            "ssh_url": "git@github.com:utkarshagarwal/TwitterRelationExtractor.git",
            "language": ""
         }
      ]
   },
   {
      "user": "https://github.com/vivekravisankar",
      "repos": [
         {
            "url": "https://github.com/vivekravisankar/Vivek-Ravisankar-SFDC-1",
            "ssh_url": "git@github.com:vivekravisankar/Vivek-Ravisankar-SFDC-1.git",
            "language": ""
         }
      ]
   }
]