[
   {
      "user": "https://github.com/adambennis",
      "repos": [
         {
            "url": "https://github.com/adambennis/rds-pg-dev",
            "ssh_url": "git@github.com:adambennis/rds-pg-dev.git",
            "language": "HCL"
         },
         {
            "url": "https://github.com/adambennis/rds-orc-dev",
            "ssh_url": "git@github.com:adambennis/rds-orc-dev.git",
            "language": "HCL"
         }
      ]
   },
   {
      "user": "https://github.com/frontendDeveloper",
      "repos": [
         {
            "url": "https://github.com/frontendDeveloper/test",
            "ssh_url": "git@github.com:frontendDeveloper/test.git",
            "language": ""
         }
      ]
   },
   {
      "user": "https://github.com/johnkanel",
      "repos": [
         {
            "url": "https://github.com/johnkanel/Module-2",
            "ssh_url": "git@github.com:johnkanel/Module-2.git",
            "language": "HTML"
         },
         {
            "url": "https://github.com/johnkanel/fisrt",
            "ssh_url": "git@github.com:johnkanel/fisrt.git",
            "language": ""
         }
      ]
   },
   {
      "user": "https://github.com/nicolasrobles",
      "repos": [
         {
            "url": "https://github.com/nicolasrobles/LSEJava",
            "ssh_url": "git@github.com:nicolasrobles/LSEJava.git",
            "language": "Java"
         },
         {
            "url": "https://github.com/nicolasrobles/WeilGeneralized",
            "ssh_url": "git@github.com:nicolasrobles/WeilGeneralized.git",
            "language": "Mathematica"
         },
         {
            "url": "https://github.com/nicolasrobles/CohenRamanujanSums",
            "ssh_url": "git@github.com:nicolasrobles/CohenRamanujanSums.git",
            "language": "Mathematica"
         },
         {
            "url": "https://github.com/nicolasrobles/Largest-gap-between-zeros",
            "ssh_url": "git@github.com:nicolasrobles/Largest-gap-between-zeros.git",
            "language": "Mathematica"
         },
         {
            "url": "https://github.com/nicolasrobles/WolframRH",
            "ssh_url": "git@github.com:nicolasrobles/WolframRH.git",
            "language": "Mathematica"
         },
         {
            "url": "https://github.com/nicolasrobles/Combinatorial-applications-of-autocorrelation-ratios",
            "ssh_url": "git@github.com:nicolasrobles/Combinatorial-applications-of-autocorrelation-ratios.git",
            "language": "Mathematica"
         },
         {
            "url": "https://github.com/nicolasrobles/MomentsCohenRamanujan",
            "ssh_url": "git@github.com:nicolasrobles/MomentsCohenRamanujan.git",
            "language": "Mathematica"
         },
         {
            "url": "https://github.com/nicolasrobles/WolframGeometry",
            "ssh_url": "git@github.com:nicolasrobles/WolframGeometry.git",
            "language": "Mathematica"
         }
      ]
   },
   {
      "user": "https://github.com/petercote",
      "repos": [
         {
            "url": "https://github.com/petercote/PB-Machine-2.1",
            "ssh_url": "git@github.com:petercote/PB-Machine-2.1.git",
            "language": "C++"
         },
         {
            "url": "https://github.com/petercote/stepper-pot-test",
            "ssh_url": "git@github.com:petercote/stepper-pot-test.git",
            "language": "C++"
         },
         {
            "url": "https://github.com/petercote/PB-Machine-2.0",
            "ssh_url": "git@github.com:petercote/PB-Machine-2.0.git",
            "language": "C++"
         }
      ]
   }
]